lakeel/__init__.py
lakeel/lakeel.py
lakeel-0.0.5.dist-info/LICENSE
lakeel-0.0.5.dist-info/METADATA
lakeel-0.0.5.dist-info/WHEEL
lakeel-0.0.5.dist-info/top_level.txt
lakeel-0.0.5.dist-info/RECORD
